sparkparse/__init__.py
sparkparse/app.py
sparkparse/clean.py
sparkparse/common.py
sparkparse/dashboard.py
sparkparse/models.py
sparkparse/parse.py
sparkparse/styling.py
sparkparse/viz.py
sparkparse/assets/css/style.css
sparkparse/assets/fonts/jetbrainsmonoregular.woff2
sparkparse/pages/dag.py
sparkparse/pages/home.py
sparkparse/pages/summary.py
sparkparse-0.1.0.dist-info/METADATA
sparkparse-0.1.0.dist-info/WHEEL
sparkparse-0.1.0.dist-info/entry_points.txt
sparkparse-0.1.0.dist-info/RECORD
